gen_doc/__init__.py
gen_doc/main.py
GenDoc-1.0.1.dist-info/LICENSE
GenDoc-1.0.1.dist-info/METADATA
GenDoc-1.0.1.dist-info/WHEEL
GenDoc-1.0.1.dist-info/entry_points.txt
GenDoc-1.0.1.dist-info/top_level.txt
GenDoc-1.0.1.dist-info/RECORD
