Metadata-Version: 2.1
Name: GenDoc
Version: 1.0.1
Summary: Generate a Markdown Documentation file from a Python Repository with DocStrings.
Home-page: https://github.com/http-samc/GenDoc
Author: Samarth Chitgopekar
Author-email: sam@chitgopekar.tech
License: UNKNOWN
Platform: UNKNOWN
Classifier: Topic :: Utilities
Classifier: Intended Audience :: Developers
Classifier: Environment :: Console
Classifier: Development Status :: 5 - Production/Stable
Classifier: License :: OSI Approved :: MIT License
Classifier: Operating System :: OS Independent
Classifier: Programming Language :: Python :: 3.9
Classifier: Natural Language :: English
